LICENSE
MANIFEST.in
README.rst
pytest_pydev.py
setup.py
pytest_pydev.egg-info/PKG-INFO
pytest_pydev.egg-info/SOURCES.txt
pytest_pydev.egg-info/dependency_links.txt
pytest_pydev.egg-info/entry_points.txt
pytest_pydev.egg-info/requires.txt
pytest_pydev.egg-info/top_level.txt