Metadata-Version: 1.0
Name: pytest-pydev
Version: 0.1
Summary: py.test plugin to connect to a remote debug server with PyDev or PyCharm.
Home-page: http://bitbucket.org/basti/pytest-pydev/
Author: Sebastian Rahlf
Author-email: basti AT redtoad DOT de
License: MIT License
Download-URL: http://bitbucket.org/basti/pytest-pydev/downloads/
Keywords: py.test,pytest,pydev,pycharm,python remote debugger
Platform: UNKNOWN
Classifier: Operating System :: OS Independent
Classifier: Development Status :: 3 - Alpha
Classifier: Intended Audience :: Developers
Classifier: License :: OSI Approved :: MIT License
Classifier: Programming Language :: Python :: 2.4
Classifier: Programming Language :: Python :: 2.5
Classifier: Programming Language :: Python :: 2.6
Classifier: Programming Language :: Python :: 2.7
Classifier: Topic :: Software Development :: Testing
